mkmusic/__init__.py
mkmusic/instrument.py
mkmusic/mclass.py
mkmusic/readfile.py
mkmusic/table.py
mkmusic/version.py
mkmusic-1.0.0a2.dist-info/LICENSE
mkmusic-1.0.0a2.dist-info/METADATA
mkmusic-1.0.0a2.dist-info/WHEEL
mkmusic-1.0.0a2.dist-info/entry_points.txt
mkmusic-1.0.0a2.dist-info/top_level.txt
mkmusic-1.0.0a2.dist-info/RECORD
